setup.py
bosh/__init__.py
bosh/bosh.py
bosh/boshC3.py
bosh/boshExcel.py
bosh/csvloader.py
bosh/dbop.py
bosh/docSql.py
bosh/rpcshell.py
bosh/send_receive.py
bosh/tools.py
bosh.egg-info/PKG-INFO
bosh.egg-info/SOURCES.txt
bosh.egg-info/dependency_links.txt
bosh.egg-info/entry_points.txt
bosh.egg-info/not-zip-safe
bosh.egg-info/requires.txt
bosh.egg-info/top_level.txt