Metadata-Version: 1.0
Name: bosh
Version: 0.2.25
Summary: BigObject service command line tool
Home-page: https://github.com/bigobject-inc/bosh.git
Author: MacroData Inc
Author-email: info@macrodatalab.com
License: Apache 2.0
Keywords: bigobject,macrodata,analytics,command line tool
Platform: UNKNOWN
